cleanlib/__init__.py
cleanlib/main.py
cleanlib-0.0.1.dist-info/METADATA
cleanlib-0.0.1.dist-info/WHEEL
cleanlib-0.0.1.dist-info/top_level.txt
cleanlib-0.0.1.dist-info/RECORD
